AUTHORS.txt
CHANGES.rst
CLASSIFIERS.txt
LICENSE
MANIFEST.in
README.rst
REQUIREMENTS.txt
setup.py
pypiweb/__init__.py
pypiweb/__init__.pyc
pypiweb/__main__.py
pypiweb/_app.py
pypiweb/bottle.py
pypiweb/core.py
pypiweb/manage.py
pypiweb/welcome.html
pypiweb.egg-info/PKG-INFO
pypiweb.egg-info/SOURCES.txt
pypiweb.egg-info/dependency_links.txt
pypiweb.egg-info/entry_points.txt
pypiweb.egg-info/requires.txt
pypiweb.egg-info/top_level.txt
pypiweb/template/packages.tpl
pypiweb/template/pypiindex.tpl
pypiweb/template/pypipkg.tpl
pypiweb/template/simple.tpl
pypiweb/template/simpleprefix.tpl
pypiweb/template/welcome.tpl